qr_upn/__init__.py
qr_upn/codes.csv
qr_upn/courbd.ttf
qr_upn/formaters.py
qr_upn/misc.py
qr_upn/rules.py
qr_upn/upn_sl.png
qr_upn/utils.py
qr_upn-1.2.0.dist-info/METADATA
qr_upn-1.2.0.dist-info/WHEEL
qr_upn-1.2.0.dist-info/licenses/LICENSE
qr_upn-1.2.0.dist-info/RECORD
