Metadata-Version: 2.1
Name: qr_upn
Version: 1.2.0
Summary: A small package which will generate a QR UPN.
Project-URL: Homepage, https://github.com/peterhorvat/QR-UPN
Project-URL: Bug Tracker, https://github.com/peterhorvat/QR-UPN/issues
Author-email: Peter Horvat <peter.horvat85@gmail.com>
License: Copyright (c) 2018 The Python Packaging Authority
License-File: LICENSE
Classifier: License :: OSI Approved :: MIT License
Classifier: Operating System :: OS Independent
Classifier: Programming Language :: Python :: 3
Requires-Python: >=3.9.7
